Metadata-Version: 1.1
Name: cogroo-interface
Version: 0.3.5
Summary: Interface for accessing CoGrOO from Python scripts using py4j
Home-page: https://github.com/kevencarneiro/cogroo4py
Author: Guilherme Passero
Author-email: guilherme.passero0@gmail.com
License: UNKNOWN
Keywords: cogroo
Platform: UNKNOWN
Classifier: Programming Language :: Python :: 3
Classifier: Intended Audience :: Developers
Classifier: Natural Language :: Portuguese (Brazilian)
Classifier: Operating System :: OS Independent
Classifier: Topic :: Text Processing
